[
    {
       "name":"Ramesh",
       "id":123,
       "age":40,
       "weight":"70kg",
       "friends":[
          {
             "name":"Monika",
             "id":989,
             "age":25,
             "weight":"30kg",
             "friends":[
                {
                   "name":"Ajit",
                   "id":434,
                   "age":30,
                   "weight":"50kg",
                   "friends":[
                      
                   ]
                }
             ]
          },
          {
             "name":"Rahul",
             "id":565,
             "age":45,
             "weight":"80kg",
             "friends":[
                {
                   "name":"Sunny",
                   "id":789,
                   "age":50,
                   "weight":"69kg",
                   "friends":[
                      
                   ]
                }
             ]
          }
       ]
    },
    {
       "name":"Sheetal",
       "id":578,
       "age":40,
       "weight":"70kg",
       "friends":[
          {
             "name":"Chubb",
             "id":343,
             "age":25,
             "weight":"30kg",
             "friends":[
                {
                   "name":"Mike",
                   "id":112,
                   "age":30,
                   "weight":"50kg",
                   "friends":[
                      
                   ]
                }
             ]
          },
          {
             "name":"Michael",
             "id":800,
             "age":45,
             "weight":"80kg",
             "friends":[
                {
                   "name":"Viki",
                   "id":343,
                   "age":50,
                   "weight":"69kg",
                   "friends":[
                      
                   ]
                }
             ]
          }
       ]
    }
 ]